thamizhilip/__init__.py
thamizhilip/tamil.py
thamizhilip-0.11.dist-info/LICENSE
thamizhilip-0.11.dist-info/METADATA
thamizhilip-0.11.dist-info/WHEEL
thamizhilip-0.11.dist-info/top_level.txt
thamizhilip-0.11.dist-info/RECORD
