Metadata-Version: 2.1
Name: thamizhilip
Version: 0.11
Summary: ThamizhiLIP
Home-page: UNKNOWN
Author: Kengatharaiyer Sarveswaran
Author-email: <iamsarves@gmail.com>
License: Apache License, Version 2.0
Keywords: Thamizhi,Tamil,Tamil NLP
Platform: UNKNOWN
Classifier: Programming Language :: Python :: 3
Classifier: License :: OSI Approved :: Apache Software License
Classifier: Operating System :: OS Independent
Requires-Python: >=3.6
Requires-Dist: stanza
